data2cloud/cloud/maxcompute/__init__.py
data2cloud/cloud/maxcompute/initialize_maxcompute.py
data2cloud/cloud/maxcompute/instance_parser.py
data2cloud/cloud/maxcompute/mock_odps.py
data2cloud/cloud/maxcompute/sql_runner.py
data2cloud/data_uploader/__init__.py
data2cloud/data_uploader/data_config_parser.py
data2cloud/data_uploader/data_uploader.py
data2cloud/data_uploader/import_matrix.py
data2cloud/schemas/json/data-config-schema.json
data2cloud-0.0.5.dist-info/METADATA
data2cloud-0.0.5.dist-info/WHEEL
data2cloud-0.0.5.dist-info/top_level.txt
data2cloud-0.0.5.dist-info/RECORD
