Metadata-Version: 2.1
Name: data2cloud
Version: 0.0.5
Summary: upload data from oss to maxcompute and import to matrix lib table
Home-page: https://github.com/Digital-Transformation-Research-Center/data2cloud
Author: t2wei
Author-email: t2wei@me.com
Classifier: Programming Language :: Python :: 3
Classifier: License :: OSI Approved :: MIT License
Classifier: Operating System :: OS Independent
Requires-Python: >=3.7
Requires-Dist: pandas >=1.3.5
Requires-Dist: pyodps >=0.11.6
Requires-Dist: jsonschema >=4.22
